pyromocc-0.0.8.data/purelib/libzmq-v142-mt-4_3_2.lib
pyromocc-0.0.8.data/purelib/libzmq-v142-mt-s-4_3_2.lib
pyromocc-0.0.8.data/purelib/orocos-kdl.lib
pyromocc-0.0.8.data/purelib/pyromocc.cp38-win_amd64.pyd
pyromocc-0.0.8.data/purelib/pyromocc.lib
pyromocc-0.0.8.data/purelib/romocc.lib
pyromocc-0.0.8.data/purelib/pyromocc/__init__.py
pyromocc-0.0.8.data/purelib/pyromocc/concrt140.dll
pyromocc-0.0.8.data/purelib/pyromocc/libzmq-v142-mt-4_3_2.dll
pyromocc-0.0.8.data/purelib/pyromocc/libzmq-v142-mt-4_3_2.lib
pyromocc-0.0.8.data/purelib/pyromocc/libzmq-v142-mt-s-4_3_2.lib
pyromocc-0.0.8.data/purelib/pyromocc/msvcp140.dll
pyromocc-0.0.8.data/purelib/pyromocc/msvcp140_1.dll
pyromocc-0.0.8.data/purelib/pyromocc/msvcp140_2.dll
pyromocc-0.0.8.data/purelib/pyromocc/msvcp140_atomic_wait.dll
pyromocc-0.0.8.data/purelib/pyromocc/msvcp140_codecvt_ids.dll
pyromocc-0.0.8.data/purelib/pyromocc/orocos-kdl.lib
pyromocc-0.0.8.data/purelib/pyromocc/pyromocc.cp38-win_amd64.pyd
pyromocc-0.0.8.data/purelib/pyromocc/pyromocc.lib
pyromocc-0.0.8.data/purelib/pyromocc/robot.py
pyromocc-0.0.8.data/purelib/pyromocc/romocc.dll
pyromocc-0.0.8.data/purelib/pyromocc/romocc.lib
pyromocc-0.0.8.data/purelib/pyromocc/vcruntime140.dll
pyromocc-0.0.8.data/purelib/pyromocc/vcruntime140_1.dll
pyromocc-0.0.8.data/purelib/pyromocc/tools/__init__.py
pyromocc-0.0.8.data/purelib/pyromocc/tools/robotiq_gripper.py
pyromocc-0.0.8.data/purelib/pyromocc/tools/spacemouse.py
pyromocc-0.0.8.data/purelib/pyromocc/tools/urscript.py
pyromocc-0.0.8.dist-info/METADATA
pyromocc-0.0.8.dist-info/WHEEL
pyromocc-0.0.8.dist-info/top_level.txt
pyromocc-0.0.8.dist-info/RECORD
